[
  {
    "inputs": [
      {
        "internalType": "string",
        "name": "_distributorInfoCid",
        "type": "string"
      },
      {
        "internalType": "address",
        "name": "_link",
        "type": "address"
      }
    ],
    "stateMutability": "nonpayable",
    "type": "constructor"
  },
  {
    "anonymous": false,
    "inputs": [
      {
        "indexed": true,
        "internalType": "address",
        "name": "campaign",
        "type": "address"
      },
      {
        "indexed": true,
        "internalType": "address",
        "name": "token",
        "type": "address"
      },
      {
        "indexed": true,
        "internalType": "address",
        "name": "creator",
        "type": "address"
      }
    ],
    "name": "CreateCampaign",
    "type": "event"
  },
  {
    "inputs": [
      {
        "internalType": "uint256",
        "name": "",
        "type": "uint256"
      }
    ],
    "name": "campaignList",
    "outputs": [
      {
        "internalType": "address",
        "name": "",
        "type": "address"
      }
    ],
    "stateMutability": "view",
    "type": "function"
  },
  {
    "inputs": [],
    "name": "distributorInfoCid",
    "outputs": [
      {
        "internalType": "string",
        "name": "",
        "type": "string"
      }
    ],
    "stateMutability": "view",
    "type": "function"
  },
  {
    "inputs": [],
    "name": "link",
    "outputs": [
      {
        "internalType": "address",
        "name": "",
        "type": "address"
      }
    ],
    "stateMutability": "view",
    "type": "function"
  },
  {
    "inputs": [],
    "name": "nextCampaignId",
    "outputs": [
      {
        "internalType": "uint256",
        "name": "",
        "type": "uint256"
      }
    ],
    "stateMutability": "view",
    "type": "function"
  },
  {
    "inputs": [
      {
        "internalType": "address payable",
        "name": "token",
        "type": "address"
      },
      {
        "internalType": "address",
        "name": "tokenSender",
        "type": "address"
      },
      {
        "internalType": "string",
        "name": "campaignInfoCid",
        "type": "string"
      },
      {
        "internalType": "string",
        "name": "recipientsCid",
        "type": "string"
      },
      {
        "internalType": "uint32",
        "name": "recipientsNum",
        "type": "uint32"
      },
      {
        "internalType": "uint256",
        "name": "startDate",
        "type": "uint256"
      },
      {
        "internalType": "uint256",
        "name": "endDate",
        "type": "uint256"
      }
    ],
    "name": "createCampaign",
    "outputs": [],
    "stateMutability": "nonpayable",
    "type": "function"
  }
]
